{"version": 0.6, "generator": "Overpass API 0.7.62.5 1bd436f1", "osm3s": {"timestamp_osm_base": "2025-03-28T18:51:00Z", "copyright": "The data included in this document is from www.openstreetmap.org. The data is made available under ODbL."}, "elements": [{"type": "node", "id": 5792255054, "lat": 40.8727543, "lon": 29.1257438, "tags": {"amenity": "school", "name": "Adakademi"}}, {"type": "node", "id": 6950305344, "lat": 40.8695127, "lon": 29.1275203}, {"type": "node", "id": 6950305345, "lat": 40.8691096, "lon": 29.1274402}, {"type": "node", "id": 6950305346, "lat": 40.8689465, "lon": 29.1279301}, {"type": "node", "id": 6950305347, "lat": 40.8694871, "lon": 29.1280441}, {"type": "way", "id": 742393689, "nodes": [6950305344, 6950305345, 6950305346, 6950305347, 6950305344], "tags": {"amenity": "school", "name": "B\u00fcy\u00fckada \u015eehit Murat Y\u00fcksel \u0130lkokulu"}}]}